LbConfiguration/Platform.py
LbConfiguration/__init__.py
LbConfiguration/SP2/__init__.py
LbConfiguration/SP2/lookup.py
LbConfiguration/SP2/version.py
LbConfiguration-0.1.0.dist-info/METADATA
LbConfiguration-0.1.0.dist-info/WHEEL
LbConfiguration-0.1.0.dist-info/top_level.txt
LbConfiguration-0.1.0.dist-info/RECORD
