Metadata-Version: 2.1
Name: LbConfiguration
Version: 0.1.0
Summary: LbConfiguration. Here only used for creating doxygen configuration
Home-page: https://github.com/shuds13/pyexample
Author: Piet Nogga
Author-email: piet.nogga@cern.ch
License: BSD 2-clause
Classifier: Development Status :: 1 - Planning
Classifier: Intended Audience :: Science/Research
Classifier: Operating System :: POSIX :: Linux
Classifier: Programming Language :: Python :: 3.9
